django_whoop/__init__.py
django_whoop/admin.py
django_whoop/apps.py
django_whoop/forms.py
django_whoop/models.py
django_whoop/tests.py
django_whoop/urls.py
django_whoop/views.py
django_whoop/migrations/0001_initial.py
django_whoop/migrations/0002_auto_20210317_1359.py
django_whoop/migrations/0003_auto_20210317_1424.py
django_whoop/migrations/0004_auto_20210317_1430.py
django_whoop/migrations/0005_daily_recovery_sleep_sleepdetail_strain_workout.py
django_whoop/migrations/0006_auto_20210318_1359.py
django_whoop/migrations/0007_auto_20210318_1400.py
django_whoop/migrations/0008_auto_20210318_1416.py
django_whoop/migrations/0009_hr.py
django_whoop/migrations/0010_journalentry.py
django_whoop/migrations/__init__.py
django_whoop/templates/whoop/base.html
django_whoop/templates/whoop/login.html
django_whoop/templates/whoop/reauth.html
django_whoop/templates/whoop/success.html
django_whoop-0.1.dist-info/LICENSE
django_whoop-0.1.dist-info/METADATA
django_whoop-0.1.dist-info/WHEEL
django_whoop-0.1.dist-info/top_level.txt
django_whoop-0.1.dist-info/RECORD
